{
  "refurbished_furniture:recipes/misc/slicing/brown_dye_from_rotten_flesh": {
    "criteria": {
      "has_rotten_flesh": "2025-06-29 01:00:29 +0000"
    },
    "done": true
  },
  "regions_unexplored:recipes/building_blocks/lime_painted_planks": {
    "criteria": {
      "has_planks": "2025-06-29 00:47:58 +0000"
    },
    "done": true
  },
  "refurbished_furniture:recipes/misc/constructing/purple_stool": {
    "criteria": {
      "has_planks": "2025-06-29 00:47:58 +0000"
    },
    "done": true
  },
  "minecraft:recipes/combat/leather_helmet": {
    "criteria": {
      "has_leather": "2025-06-29 00:58:58 +0000"
    },
    "done": true
  },
  "minecraft:recipes/decorations/ladder": {
    "criteria": {
      "has_stick": "2025-06-29 00:51:19 +0000"
    },
    "done": true
  },
  "regions_unexplored:recipes/transportation/maple_boat": {
    "criteria": {
      "in_water": "2025-06-29 01:03:53 +0000"
    },
    "done": true
  },
  "mutantmonsters:root": {
    "criteria": {
      "killed_by_something": "2025-06-29 00:48:30 +0000"
    },
    "done": true
  },
  "refurbished_furniture:recipes/misc/constructing/oak_toilet": {
    "criteria": {
      "has_oak_planks": "2025-06-29 00:47:58 +0000"
    },
    "done": true
  },
  "refurbished_furniture:recipes/misc/constructing/crimson_lattice_fence": {
    "criteria": {
      "has_stick": "2025-06-29 00:51:19 +0000"
    },
    "done": true
  },
  "securitycraft:recipes/redstone/reinforced_birch_fence_gate": {
    "criteria": {
      "has_stick": "2025-06-29 00:51:19 +0000"
    },
    "done": true
  },
  "securitycraft:recipes/redstone/reinforced_crimson_fence_gate": {
    "criteria": {
      "has_stick": "2025-06-29 00:51:19 +0000"
    },
    "done": true
  },
  "refurbished_furniture:recipes/misc/constructing/jungle_lattice_fence": {
    "criteria": {
      "has_stick": "2025-06-29 00:51:19 +0000"
    },
    "done": true
  },
  "securitycraft:recipes/misc/motion_activated_light": {
    "criteria": {
      "has_stick": "2025-06-29 00:51:19 +0000"
    },
    "done": true
  },
  "refurbished_furniture:recipes/misc/constructing/spruce_table": {
    "criteria": {
      "has_spruce_planks": "2025-06-29 00:51:07 +0000"
    },
    "done": true
  },
  "securitycraft:recipes/redstone/reinforced_jungle_fence_gate": {
    "criteria": {
      "has_stick": "2025-06-29 00:51:19 +0000"
    },
    "done": true
  },
  "refurbished_furniture:recipes/misc/constructing/spruce_lattice_fence_gate": {
    "criteria": {
      "has_spruce_planks": "2025-06-29 00:51:07 +0000"
    },
    "done": true
  },
  "refurbished_furniture:recipes/misc/constructing/green_stool": {
    "criteria": {
      "has_planks": "2025-06-29 00:47:58 +0000"
    },
    "done": true
  },
  "minecraft:recipes/decorations/fletching_table": {
    "criteria": {
      "has_flint": "2025-06-29 01:04:12 +0000"
    },
    "done": true
  },
  "create:recipes/misc/crafting/kinetics/steam_whistle": {
    "criteria": {
      "has_item": "2025-06-29 01:06:07 +0000"
    },
    "done": true
  },
  "refurbished_furniture:recipes/misc/constructing/yellow_lamp": {
    "criteria": {
      "has_planks": "2025-06-29 00:47:58 +0000"
    },
    "done": true
  },
  "refurbished_furniture:recipes/misc/constructing/oak_kitchen_drawer": {
    "criteria": {
      "has_oak_planks": "2025-06-29 00:47:58 +0000"
    },
    "done": true
  },
  "refurbished_furniture:recipes/misc/constructing/spruce_kitchen_sink": {
    "criteria": {
      "has_spruce_planks": "2025-06-29 00:51:07 +0000"
    },
    "done": true
  },
  "refurbished_furniture:recipes/misc/constructing/dark_oak_toilet": {
    "criteria": {
      "has_copper_ingot": "2025-06-29 01:06:07 +0000"
    },
    "done": true
  },
  "minecraft:recipes/decorations/oak_sign": {
    "criteria": {
      "has_planks": "2025-06-29 00:47:58 +0000"
    },
    "done": true
  },
  "refurbished_furniture:recipes/misc/constructing/cherry_bath": {
    "criteria": {
      "has_copper_ingot": "2025-06-29 01:06:07 +0000"
    },
    "done": true
  },
  "refurbished_furniture:recipes/misc/spatula": {
    "criteria": {
      "has_leather": "2025-06-29 00:58:58 +0000"
    },
    "done": true
  },
  "refurbished_furniture:recipes/misc/constructing/acacia_bath": {
    "criteria": {
      "has_copper_ingot": "2025-06-29 01:06:07 +0000"
    },
    "done": true
  },
  "refurbished_furniture:recipes/misc/constructing/red_lamp": {
    "criteria": {
      "has_planks": "2025-06-29 00:47:58 +0000"
    },
    "done": true
  },
  "create:recipes/misc/crafting/appliances/copper_backtank": {
    "criteria": {
      "has_item": "2025-06-29 01:06:07 +0000"
    },
    "done": true
  },
  "refurbished_furniture:recipes/misc/constructing/warped_kitchen_sink": {
    "criteria": {
      "has_copper_ingot": "2025-06-29 01:06:07 +0000"
    },
    "done": true
  },
  "refurbished_furniture:recipes/misc/constructing/orange_lamp": {
    "criteria": {
      "has_planks": "2025-06-29 00:47:58 +0000"
    },
    "done": true
  },
  "bunker_down:first_joined_world": {
    "criteria": {
      "first_joined_world": "2025-06-29 00:43:28 +0000"
    },
    "done": true
  },
  "refurbished_furniture:recipes/misc/constructing/dark_oak_lattice_fence_gate": {
    "criteria": {
      "has_stick": "2025-06-29 00:51:19 +0000"
    },
    "done": true
  },
  "refurbished_furniture:recipes/misc/constructing/crimson_toilet": {
    "criteria": {
      "has_copper_ingot": "2025-06-29 01:06:07 +0000"
    },
    "done": true
  },
  "refurbished_furniture:recipes/misc/constructing/birch_kitchen_sink": {
    "criteria": {
      "has_copper_ingot": "2025-06-29 01:06:07 +0000"
    },
    "done": true
  },
  "minecraft:story/mine_stone": {
    "criteria": {
      "get_stone": "2025-06-29 00:57:17 +0000"
    },
    "done": true
  },
  "minecraft:recipes/decorations/furnace": {
    "criteria": {
      "has_cobblestone": "2025-06-29 00:57:17 +0000"
    },
    "done": true
  },
  "create:root": {
    "criteria": {
      "0": "2025-06-29 00:47:40 +0000"
    },
    "done": true
  },
  "minecraft:recipes/tools/wooden_axe": {
    "criteria": {
      "has_stick": "2025-06-29 00:51:19 +0000"
    },
    "done": true
  },
  "create:copper": {
    "criteria": {
      "0": "2025-06-29 01:06:07 +0000"
    },
    "done": true
  },
  "regions_unexplored:recipes/transportation/magnolia_boat": {
    "criteria": {
      "in_water": "2025-06-29 01:03:53 +0000"
    },
    "done": true
  },
  "refurbished_furniture:recipes/misc/constructing/spruce_kitchen_drawer": {
    "criteria": {
      "has_spruce_planks": "2025-06-29 00:51:07 +0000"
    },
    "done": true
  },
  "refurbished_furniture:recipes/misc/constructing/white_lamp": {
    "criteria": {
      "has_planks": "2025-06-29 00:47:58 +0000"
    },
    "done": true
  },
  "minecraft:recipes/combat/leather_chestplate": {
    "criteria": {
      "has_leather": "2025-06-29 00:58:58 +0000"
    },
    "done": true
  },
  "create:recipes/misc/crafting/appliances/crafting_blueprint": {
    "criteria": {
      "has_item": "2025-06-29 00:51:12 +0000"
    },
    "done": true
  },
  "securitycraft:recipes/redstone/reinforced_spruce_fence_gate": {
    "criteria": {
      "has_stick": "2025-06-29 00:51:19 +0000"
    },
    "done": true
  },
  "refurbished_furniture:recipes/misc/constructing/yellow_sofa": {
    "criteria": {
      "has_planks": "2025-06-29 00:47:58 +0000"
    },
    "done": true
  },
  "securitycraft:recipes/building_blocks/reinforced_andesite_with_vanilla_diorite": {
    "criteria": {
      "has_cobblestone": "2025-06-29 00:57:17 +0000"
    },
    "done": true
  },
  "refurbished_furniture:recipes/misc/constructing/orange_sofa": {
    "criteria": {
      "has_planks": "2025-06-29 00:47:58 +0000"
    },
    "done": true
  },
  "regions_unexplored:recipes/building_blocks/brown_painted_planks": {
    "criteria": {
      "has_planks": "2025-06-29 00:47:58 +0000"
    },
    "done": true
  },
  "minecraft:recipes/decorations/crafting_table": {
    "criteria": {
      "unlock_right_away": "2025-06-29 00:43:28 +0000"
    },
    "done": true
  },
  "minecraft:recipes/decorations/chest": {
    "criteria": {
      "has_lots_of_items": "2025-06-29 00:58:58 +0000"
    },
    "done": true
  },
  "minecraft:recipes/misc/stick": {
    "criteria": {
      "has_planks": "2025-06-29 00:47:58 +0000"
    },
    "done": true
  },
  "create:recipes/misc/crafting/kinetics/steam_engine": {
    "criteria": {
      "has_item": "2025-06-29 01:06:07 +0000"
    },
    "done": true
  },
  "mca:recipes/decorations/red_spruce_crib": {
    "criteria": {
      "has_spruce_planks": "2025-06-29 00:51:07 +0000"
    },
    "done": true
  },
  "refurbished_furniture:recipes/misc/constructing/oak_crate": {
    "criteria": {
      "has_oak_planks": "2025-06-29 00:47:58 +0000"
    },
    "done": true
  },
  "minecraft:adventure/sleep_in_bed": {
    "criteria": {
      "slept_in_bed": "2025-06-29 00:53:43 +0000"
    },
    "done": true
  },
  "refurbished_furniture:recipes/misc/constructing/spruce_kitchen_storage_cabinet": {
    "criteria": {
      "has_spruce_planks": "2025-06-29 00:51:07 +0000"
    },
    "done": true
  },
  "minecraft:recipes/building_blocks/cobblestone_slab_from_cobblestone_stonecutting": {
    "criteria": {
      "has_cobblestone": "2025-06-29 00:57:17 +0000"
    },
    "done": true
  },
  "minecraft:recipes/transportation/cherry_boat": {
    "criteria": {
      "in_water": "2025-06-29 01:03:53 +0000"
    },
    "done": true
  },
  "mca:recipes/decorations/orange_spruce_crib": {
    "criteria": {
      "has_spruce_planks": "2025-06-29 00:51:07 +0000"
    },
    "done": true
  },
  "minecraft:recipes/redstone/lightning_rod": {
    "criteria": {
      "has_copper_ingot": "2025-06-29 01:06:07 +0000"
    },
    "done": true
  },
  "minecraft:adventure/kill_all_mobs": {
    "criteria": {
      "minecraft:zombie": "2025-06-29 00:56:32 +0000",
      "minecraft:drowned": "2025-06-29 01:06:07 +0000"
    },
    "done": false
  },
  "refurbished_furniture:recipes/misc/constructing/birch_bath": {
    "criteria": {
      "has_copper_ingot": "2025-06-29 01:06:07 +0000"
    },
    "done": true
  },
  "refurbished_furniture:recipes/misc/constructing/oak_light_ceiling_fan": {
    "criteria": {
      "has_oak_planks": "2025-06-29 00:47:58 +0000"
    },
    "done": true
  },
  "mca:recipes/decorations/yellow_spruce_crib": {
    "criteria": {
      "has_spruce_planks": "2025-06-29 00:51:07 +0000"
    },
    "done": true
  },
  "refurbished_furniture:recipes/misc/constructing/spruce_bath": {
    "criteria": {
      "has_spruce_planks": "2025-06-29 00:51:07 +0000"
    },
    "done": true
  },
  "refurbished_furniture:recipes/misc/constructing/dark_oak_kitchen_sink": {
    "criteria": {
      "has_copper_ingot": "2025-06-29 01:06:07 +0000"
    },
    "done": true
  },
  "mca:recipes/decorations/pink_spruce_crib": {
    "criteria": {
      "has_spruce_planks": "2025-06-29 00:51:07 +0000"
    },
    "done": true
  },
  "refurbished_furniture:recipes/misc/constructing/oak_lattice_fence_gate": {
    "criteria": {
      "has_oak_planks": "2025-06-29 00:47:58 +0000"
    },
    "done": true
  },
  "minecraft:recipes/building_blocks/stone": {
    "criteria": {
      "has_cobblestone": "2025-06-29 00:57:17 +0000"
    },
    "done": true
  },
  "refurbished_furniture:recipes/misc/constructing/birch_toilet": {
    "criteria": {
      "has_copper_ingot": "2025-06-29 01:06:07 +0000"
    },
    "done": true
  },
  "minecraft:recipes/transportation/bamboo_raft": {
    "criteria": {
      "in_water": "2025-06-29 01:03:53 +0000"
    },
    "done": true
  },
  "refurbished_furniture:recipes/misc/constructing/spruce_storage_jar": {
    "criteria": {
      "has_spruce_planks": "2025-06-29 00:51:07 +0000"
    },
    "done": true
  },
  "refurbished_furniture:recipes/misc/constructing/crimson_basin": {
    "criteria": {
      "has_copper_ingot": "2025-06-29 01:06:07 +0000"
    },
    "done": true
  },
  "refurbished_furniture:recipes/misc/constructing/magenta_stool": {
    "criteria": {
      "has_planks": "2025-06-29 00:47:58 +0000"
    },
    "done": true
  },
  "securitycraft:recipes/building_blocks/reinforced_andesite_with_vanilla_cobblestone": {
    "criteria": {
      "has_cobblestone": "2025-06-29 00:57:17 +0000"
    },
    "done": true
  },
  "refurbished_furniture:recipes/misc/constructing/oak_drawer": {
    "criteria": {
      "has_oak_planks": "2025-06-29 00:47:58 +0000"
    },
    "done": true
  },
  "regions_unexplored:recipes/building_blocks/ash": {
    "criteria": {
      "has_gunpowder": "2025-06-29 01:00:29 +0000"
    },
    "done": true
  },
  "regions_unexplored:recipes/building_blocks/black_painted_planks": {
    "criteria": {
      "has_planks": "2025-06-29 00:47:58 +0000"
    },
    "done": true
  },
  "create:recipes/building_blocks/copper_tiles_from_ingots_copper_stonecutting": {
    "criteria": {
      "has_ingots_copper": "2025-06-29 01:06:07 +0000"
    },
    "done": true
  },
  "minecraft:recipes/misc/leather_horse_armor": {
    "criteria": {
      "has_leather": "2025-06-29 00:58:58 +0000"
    },
    "done": true
  },
  "refurbished_furniture:recipes/misc/constructing/birch_lattice_fence": {
    "criteria": {
      "has_stick": "2025-06-29 00:51:19 +0000"
    },
    "done": true
  },
  "refurbished_furniture:recipes/misc/constructing/spruce_light_ceiling_fan": {
    "criteria": {
      "has_spruce_planks": "2025-06-29 00:51:07 +0000"
    },
    "done": true
  },
  "create:recipes/misc/crafting/appliances/copper_diving_helmet": {
    "criteria": {
      "has_item": "2025-06-29 01:06:07 +0000"
    },
    "done": true
  },
  "superbwarfare:main/blueprint": {
    "criteria": {
      "0": "2025-06-29 01:04:24 +0000"
    },
    "done": true
  },
  "minecraft:recipes/decorations/spruce_fence": {
    "criteria": {
      "has_planks": "2025-06-29 00:51:07 +0000"
    },
    "done": true
  },
  "securitycraft:recipes/misc/reinforced_acacia_fence": {
    "criteria": {
      "has_stick": "2025-06-29 00:51:19 +0000"
    },
    "done": true
  },
  "mca:recipes/decorations/white_spruce_crib": {
    "criteria": {
      "has_spruce_planks": "2025-06-29 00:51:07 +0000"
    },
    "done": true
  },
  "refurbished_furniture:recipes/misc/constructing/brown_cooler": {
    "criteria": {
      "has_planks": "2025-06-29 00:47:58 +0000"
    },
    "done": true
  },
  "regions_unexplored:recipes/transportation/kapok_boat": {
    "criteria": {
      "in_water": "2025-06-29 01:03:53 +0000"
    },
    "done": true
  },
  "regions_unexplored:recipes/transportation/cypress_boat": {
    "criteria": {
      "in_water": "2025-06-29 01:03:53 +0000"
    },
    "done": true
  },
  "create:recipes/building_blocks/spruce_window": {
    "criteria": {
      "has_ingredient": "2025-06-29 00:51:07 +0000"
    },
    "done": true
  },
  "refurbished_furniture:recipes/misc/constructing/mangrove_toilet": {
    "criteria": {
      "has_copper_ingot": "2025-06-29 01:06:07 +0000"
    },
    "done": true
  },
  "refurbished_furniture:recipes/misc/constructing/purple_cooler": {
    "criteria": {
      "has_planks": "2025-06-29 00:47:58 +0000"
    },
    "done": true
  },
  "regions_unexplored:recipes/building_blocks/cyan_painted_planks": {
    "criteria": {
      "has_planks": "2025-06-29 00:47:58 +0000"
    },
    "done": true
  },
  "refurbished_furniture:recipes/misc/constructing/cyan_cooler": {
    "criteria": {
      "has_planks": "2025-06-29 00:47:58 +0000"
    },
    "done": true
  },
  "create:recipes/misc/crafting/kinetics/fluid_pipe_vertical": {
    "criteria": {
      "has_item": "2025-06-29 01:06:07 +0000"
    },
    "done": true
  },
  "refurbished_furniture:recipes/misc/constructing/light_gray_cooler": {
    "criteria": {
      "has_planks": "2025-06-29 00:47:58 +0000"
    },
    "done": true
  },
  "refurbished_furniture:recipes/misc/constructing/red_sofa": {
    "criteria": {
      "has_planks": "2025-06-29 00:47:58 +0000"
    },
    "done": true
  },
  "create:recipes/misc/crafting/kinetics/mechanical_pump": {
    "criteria": {
      "has_item": "2025-06-29 01:06:07 +0000"
    },
    "done": true
  },
  "minecraft:recipes/building_blocks/copper_block": {
    "criteria": {
      "has_copper_ingot": "2025-06-29 01:06:07 +0000"
    },
    "done": true
  },
  "minecraft:recipes/redstone/spruce_button": {
    "criteria": {
      "has_planks": "2025-06-29 00:51:07 +0000"
    },
    "done": true
  },
  "refurbished_furniture:recipes/misc/constructing/spruce_mail_box": {
    "criteria": {
      "has_spruce_planks": "2025-06-29 00:51:07 +0000"
    },
    "done": true
  },
  "refurbished_furniture:recipes/misc/constructing/lime_stool": {
    "criteria": {
      "has_planks": "2025-06-29 00:47:58 +0000"
    },
    "done": true
  },
  "securitycraft:recipes/redstone/reinforced_bamboo_fence_gate": {
    "criteria": {
      "has_stick": "2025-06-29 00:51:19 +0000"
    },
    "done": true
  },
  "refurbished_furniture:recipes/misc/constructing/warped_bath": {
    "criteria": {
      "has_copper_ingot": "2025-06-29 01:06:07 +0000"
    },
    "done": true
  },
  "sophisticatedbackpacks:recipes/misc/backpack": {
    "criteria": {
      "has_leather": "2025-06-29 00:58:58 +0000"
    },
    "done": true
  },
  "minecraft:recipes/food/cooked_beef_from_smoking": {
    "criteria": {
      "has_beef": "2025-06-29 00:57:29 +0000"
    },
    "done": true
  },
  "refurbished_furniture:recipes/misc/constructing/acacia_basin": {
    "criteria": {
      "has_copper_ingot": "2025-06-29 01:06:07 +0000"
    },
    "done": true
  },
  "refurbished_furniture:recipes/misc/constructing/magenta_lamp": {
    "criteria": {
      "has_planks": "2025-06-29 00:47:58 +0000"
    },
    "done": true
  },
  "minecraft:recipes/building_blocks/oak_slab": {
    "criteria": {
      "has_planks": "2025-06-29 00:47:58 +0000"
    },
    "done": true
  },
  "minecraft:recipes/tools/brush": {
    "criteria": {
      "has_copper_ingot": "2025-06-29 01:06:07 +0000"
    },
    "done": true
  },
  "create:recipes/misc/crafting/appliances/copper_diving_boots": {
    "criteria": {
      "has_item": "2025-06-29 01:06:07 +0000"
    },
    "done": true
  },
  "minecraft:recipes/redstone/spruce_pressure_plate": {
    "criteria": {
      "has_planks": "2025-06-29 00:51:07 +0000"
    },
    "done": true
  },
  "refurbished_furniture:recipes/misc/constructing/light_gray_sofa": {
    "criteria": {
      "has_planks": "2025-06-29 00:47:58 +0000"
    },
    "done": true
  },
  "minecraft:recipes/tools/stone_pickaxe": {
    "criteria": {
      "has_cobblestone": "2025-06-29 00:57:17 +0000"
    },
    "done": true
  },
  "refurbished_furniture:recipes/misc/constructing/frying_pan": {
    "criteria": {
      "has_leather": "2025-06-29 00:58:58 +0000"
    },
    "done": true
  },
  "minecraft:recipes/decorations/lantern": {
    "criteria": {
      "has_iron_nugget": "2025-06-29 01:04:27 +0000"
    },
    "done": true
  },
  "refurbished_furniture:recipes/misc/constructing/spruce_crate": {
    "criteria": {
      "has_spruce_planks": "2025-06-29 00:51:07 +0000"
    },
    "done": true
  },
  "regions_unexplored:recipes/transportation/larch_boat": {
    "criteria": {
      "in_water": "2025-06-29 01:03:53 +0000"
    },
    "done": true
  },
  "create:recipes/building_blocks/ornate_iron_window": {
    "criteria": {
      "has_ingredient": "2025-06-29 01:04:27 +0000"
    },
    "done": true
  },
  "create:recipes/decorations/copper_table_cloth_from_ingots_copper_stonecutting": {
    "criteria": {
      "has_ingots_copper": "2025-06-29 01:06:07 +0000"
    },
    "done": true
  },
  "mca:recipes/decorations/cyan_oak_crib": {
    "criteria": {
      "has_oak_planks": "2025-06-29 00:47:58 +0000"
    },
    "done": true
  },
  "minecraft:recipes/decorations/campfire": {
    "criteria": {
      "has_stick": "2025-06-29 00:51:19 +0000"
    },
    "done": true
  },
  "refurbished_furniture:recipes/misc/constructing/dark_oak_lattice_fence": {
    "criteria": {
      "has_stick": "2025-06-29 00:51:19 +0000"
    },
    "done": true
  },
  "minecraft:recipes/tools/wooden_hoe": {
    "criteria": {
      "has_stick": "2025-06-29 00:51:19 +0000"
    },
    "done": true
  },
  "mca:recipes/decorations/light_gray_spruce_crib": {
    "criteria": {
      "has_spruce_planks": "2025-06-29 00:51:07 +0000"
    },
    "done": true
  },
  "minecraft:recipes/redstone/oak_fence_gate": {
    "criteria": {
      "has_planks": "2025-06-29 00:47:58 +0000"
    },
    "done": true
  },
  "minecraft:recipes/misc/charcoal": {
    "criteria": {
      "has_log": "2025-06-29 00:47:40 +0000"
    },
    "done": true
  },
  "refurbished_furniture:recipes/misc/constructing/acacia_lattice_fence": {
    "criteria": {
      "has_stick": "2025-06-29 00:51:19 +0000"
    },
    "done": true
  },
  "minecraft:recipes/decorations/item_frame": {
    "criteria": {
      "has_leather": "2025-06-29 00:58:58 +0000"
    },
    "done": true
  },
  "securitycraft:recipes/misc/sonic_security_system": {
    "criteria": {
      "has_stick": "2025-06-29 00:51:19 +0000"
    },
    "done": true
  },
  "regions_unexplored:recipes/decorations/spruce_branch_from_spruce_log": {
    "criteria": {
      "has_log": "2025-06-29 00:50:59 +0000"
    },
    "done": true
  },
  "refurbished_furniture:recipes/misc/constructing/oak_kitchen_storage_cabinet": {
    "criteria": {
      "has_oak_planks": "2025-06-29 00:47:58 +0000"
    },
    "done": true
  },
  "mca:recipes/decorations/blue_spruce_crib": {
    "criteria": {
      "has_spruce_planks": "2025-06-29 00:51:07 +0000"
    },
    "done": true
  },
  "regions_unexplored:recipes/decorations/oak_branch_from_oak_log": {
    "criteria": {
      "has_log": "2025-06-29 00:47:40 +0000"
    },
    "done": true
  },
  "mca:recipes/decorations/white_oak_crib": {
    "criteria": {
      "has_oak_planks": "2025-06-29 00:47:58 +0000"
    },
    "done": true
  },
  "refurbished_furniture:recipes/misc/constructing/oak_kitchen_cabinetry": {
    "criteria": {
      "has_oak_planks": "2025-06-29 00:47:58 +0000"
    },
    "done": true
  },
  "create:recipes/misc/crafting/kinetics/copper_valve_handle": {
    "criteria": {
      "has_item": "2025-06-29 01:06:07 +0000"
    },
    "done": true
  },
  "refurbished_furniture:recipes/misc/constructing/acacia_kitchen_sink": {
    "criteria": {
      "has_copper_ingot": "2025-06-29 01:06:07 +0000"
    },
    "done": true
  },
  "regions_unexplored:recipes/building_blocks/blue_painted_planks": {
    "criteria": {
      "has_planks": "2025-06-29 00:47:58 +0000"
    },
    "done": true
  },
  "minecraft:recipes/redstone/oak_door": {
    "criteria": {
      "has_planks": "2025-06-29 00:47:58 +0000"
    },
    "done": true
  },
  "refurbished_furniture:recipes/misc/constructing/oak_desk": {
    "criteria": {
      "has_oak_planks": "2025-06-29 00:47:58 +0000"
    },
    "done": true
  },
  "mca:recipes/decorations/black_spruce_crib": {
    "criteria": {
      "has_spruce_planks": "2025-06-29 00:51:07 +0000"
    },
    "done": true
  },
  "minecraft:recipes/tools/wooden_shovel": {
    "criteria": {
      "has_stick": "2025-06-29 00:51:19 +0000"
    },
    "done": true
  },
  "securitycraft:recipes/redstone/reinforced_dark_oak_fence_gate": {
    "criteria": {
      "has_stick": "2025-06-29 00:51:19 +0000"
    },
    "done": true
  },
  "minecraft:recipes/building_blocks/cobblestone_slab": {
    "criteria": {
      "has_cobblestone": "2025-06-29 00:57:17 +0000"
    },
    "done": true
  },
  "refurbished_furniture:recipes/misc/constructing/post_box": {
    "criteria": {
      "has_planks": "2025-06-29 00:47:58 +0000"
    },
    "done": true
  },
  "minecraft:recipes/transportation/acacia_boat": {
    "criteria": {
      "in_water": "2025-06-29 01:03:53 +0000"
    },
    "done": true
  },
  "minecraft:adventure/root": {
    "criteria": {
      "killed_by_something": "2025-06-29 00:48:30 +0000"
    },
    "done": true
  },
  "refurbished_furniture:recipes/misc/constructing/green_lamp": {
    "criteria": {
      "has_planks": "2025-06-29 00:47:58 +0000"
    },
    "done": true
  },
  "create:recipes/misc/crafting/kinetics/smart_fluid_pipe": {
    "criteria": {
      "has_item": "2025-06-29 01:06:07 +0000"
    },
    "done": true
  },
  "mca:recipes/building_blocks/headstones": {
    "criteria": {
      "has_ingredients": "2025-06-29 00:57:17 +0000"
    },
    "done": true
  },
  "refurbished_furniture:recipes/misc/constructing/magenta_sofa": {
    "criteria": {
      "has_planks": "2025-06-29 00:47:58 +0000"
    },
    "done": true
  },
  "minecraft:recipes/combat/wooden_sword": {
    "criteria": {
      "has_the_recipe": "2025-06-29 00:51:18 +0000"
    },
    "done": true
  },
  "minecraft:recipes/building_blocks/oak_planks": {
    "criteria": {
      "has_logs": "2025-06-29 00:47:40 +0000"
    },
    "done": true
  },
  "refurbished_furniture:recipes/misc/constructing/oak_storage_jar": {
    "criteria": {
      "has_oak_planks": "2025-06-29 00:47:58 +0000"
    },
    "done": true
  },
  "minecraft:recipes/decorations/barrel": {
    "criteria": {
      "has_planks": "2025-06-29 00:47:58 +0000"
    },
    "done": true
  },
  "refurbished_furniture:recipes/misc/constructing/oak_cutting_board": {
    "criteria": {
      "has_oak_planks": "2025-06-29 00:47:58 +0000"
    },
    "done": true
  },
  "minecraft:recipes/combat/leather_boots": {
    "criteria": {
      "has_leather": "2025-06-29 00:58:58 +0000"
    },
    "done": true
  },
  "minecraft:recipes/decorations/cobblestone_wall_from_cobblestone_stonecutting": {
    "criteria": {
      "has_cobblestone": "2025-06-29 00:57:17 +0000"
    },
    "done": true
  },
  "create:recipes/misc/crafting/kinetics/copper_valve_handle_from_others": {
    "criteria": {
      "has_item": "2025-06-29 01:06:07 +0000"
    },
    "done": true
  },
  "securitycraft:recipes/misc/reinforced_birch_fence": {
    "criteria": {
      "has_stick": "2025-06-29 00:51:19 +0000"
    },
    "done": true
  },
  "refurbished_furniture:recipes/misc/constructing/cyan_stool": {
    "criteria": {
      "has_planks": "2025-06-29 00:47:58 +0000"
    },
    "done": true
  },
  "refurbished_furniture:recipes/misc/constructing/jungle_kitchen_sink": {
    "criteria": {
      "has_copper_ingot": "2025-06-29 01:06:07 +0000"
    },
    "done": true
  },
  "minecraft:recipes/misc/firework_rocket_simple": {
    "criteria": {
      "has_gunpowder": "2025-06-29 01:00:29 +0000"
    },
    "done": true
  },
  "regions_unexplored:recipes/building_blocks/orange_painted_planks": {
    "criteria": {
      "has_planks": "2025-06-29 00:47:58 +0000"
    },
    "done": true
  },
  "securitycraft:recipes/misc/reinforced_dark_oak_fence": {
    "criteria": {
      "has_stick": "2025-06-29 00:51:19 +0000"
    },
    "done": true
  },
  "securitycraft:recipes/misc/reinforced_oak_fence": {
    "criteria": {
      "has_stick": "2025-06-29 00:51:19 +0000"
    },
    "done": true
  },
  "minecraft:recipes/building_blocks/cobblestone_stairs": {
    "criteria": {
      "has_cobblestone": "2025-06-29 00:57:17 +0000"
    },
    "done": true
  },
  "refurbished_furniture:recipes/misc/constructing/jungle_toilet": {
    "criteria": {
      "has_copper_ingot": "2025-06-29 01:06:07 +0000"
    },
    "done": true
  },
  "mca:recipes/decorations/green_oak_crib": {
    "criteria": {
      "has_oak_planks": "2025-06-29 00:47:58 +0000"
    },
    "done": true
  },
  "refurbished_furniture:recipes/misc/constructing/green_sofa": {
    "criteria": {
      "has_planks": "2025-06-29 00:47:58 +0000"
    },
    "done": true
  },
  "securitycraft:recipes/redstone/reinforced_oak_fence_gate": {
    "criteria": {
      "has_stick": "2025-06-29 00:51:19 +0000"
    },
    "done": true
  },
  "securitycraft:recipes/misc/sc_manual": {
    "criteria": {
      "has_wood": "2025-06-29 00:47:40 +0000"
    },
    "done": true
  },
  "securitycraft:recipes/misc/reinforced_bamboo_fence": {
    "criteria": {
      "has_stick": "2025-06-29 00:51:19 +0000"
    },
    "done": true
  },
  "refurbished_furniture:recipes/misc/constructing/mangrove_lattice_fence_gate": {
    "criteria": {
      "has_stick": "2025-06-29 00:51:19 +0000"
    },
    "done": true
  },
  "create:recipes/decorations/copper_bars_from_ingots_copper_stonecutting": {
    "criteria": {
      "has_ingots_copper": "2025-06-29 01:06:07 +0000"
    },
    "done": true
  },
  "securitycraft:recipes/misc/reinforced_crimson_fence": {
    "criteria": {
      "has_stick": "2025-06-29 00:51:19 +0000"
    },
    "done": true
  },
  "minecraft:recipes/tools/stone_shovel": {
    "criteria": {
      "has_cobblestone": "2025-06-29 00:57:17 +0000"
    },
    "done": true
  },
  "refurbished_furniture:recipes/misc/constructing/light_gray_lamp": {
    "criteria": {
      "has_planks": "2025-06-29 00:47:58 +0000"
    },
    "done": true
  },
  "minecraft:recipes/building_blocks/oak_wood": {
    "criteria": {
      "has_log": "2025-06-29 00:47:40 +0000"
    },
    "done": true
  },
  "regions_unexplored:parent": {
    "criteria": {
      "load_in_world": "2025-06-29 00:43:28 +0000"
    },
    "done": true
  },
  "minecraft:recipes/food/cooked_beef": {
    "criteria": {
      "has_beef": "2025-06-29 00:57:29 +0000"
    },
    "done": true
  },
  "minecraft:recipes/misc/iron_ingot_from_nuggets": {
    "criteria": {
      "has_iron_nugget": "2025-06-29 01:04:27 +0000"
    },
    "done": true
  },
  "regions_unexplored:recipes/building_blocks/gray_painted_planks": {
    "criteria": {
      "has_planks": "2025-06-29 00:47:58 +0000"
    },
    "done": true
  },
  "minecraft:recipes/transportation/jungle_boat": {
    "criteria": {
      "in_water": "2025-06-29 01:03:53 +0000"
    },
    "done": true
  },
  "refurbished_furniture:recipes/misc/constructing/jungle_lattice_fence_gate": {
    "criteria": {
      "has_stick": "2025-06-29 00:51:19 +0000"
    },
    "done": true
  },
  "regions_unexplored:recipes/transportation/blackwood_boat": {
    "criteria": {
      "in_water": "2025-06-29 01:03:53 +0000"
    },
    "done": true
  },
  "regions_unexplored:recipes/building_blocks/red_painted_planks": {
    "criteria": {
      "has_planks": "2025-06-29 00:47:58 +0000"
    },
    "done": true
  },
  "refurbished_furniture:recipes/misc/constructing/birch_basin": {
    "criteria": {
      "has_copper_ingot": "2025-06-29 01:06:07 +0000"
    },
    "done": true
  },
  "minecraft:recipes/redstone/lever": {
    "criteria": {
      "has_cobblestone": "2025-06-29 00:57:17 +0000"
    },
    "done": true
  },
  "refurbished_furniture:recipes/misc/constructing/acacia_toilet": {
    "criteria": {
      "has_copper_ingot": "2025-06-29 01:06:07 +0000"
    },
    "done": true
  },
  "refurbished_furniture:recipes/misc/constructing/blue_stool": {
    "criteria": {
      "has_planks": "2025-06-29 00:47:58 +0000"
    },
    "done": true
  },
  "minecraft:recipes/combat/leather_leggings": {
    "criteria": {
      "has_leather": "2025-06-29 00:58:58 +0000"
    },
    "done": true
  },
  "refurbished_furniture:recipes/misc/constructing/brown_stool": {
    "criteria": {
      "has_planks": "2025-06-29 00:47:58 +0000"
    },
    "done": true
  },
  "superbwarfare:recipes/combat/hunting_rifle_smithing": {
    "criteria": {
      "has_hunting_rifle_blueprint": "2025-06-29 01:04:24 +0000"
    },
    "done": true
  },
  "refurbished_furniture:recipes/misc/constructing/mangrove_bath": {
    "criteria": {
      "has_copper_ingot": "2025-06-29 01:06:07 +0000"
    },
    "done": true
  },
  "refurbished_furniture:recipes/misc/constructing/oak_kitchen_sink": {
    "criteria": {
      "has_oak_planks": "2025-06-29 00:47:58 +0000"
    },
    "done": true
  },
  "refurbished_furniture:recipes/misc/constructing/orange_stool": {
    "criteria": {
      "has_planks": "2025-06-29 00:47:58 +0000"
    },
    "done": true
  },
  "refurbished_furniture:recipes/misc/constructing/light_fridge": {
    "criteria": {
      "has_copper_ingot": "2025-06-29 01:06:07 +0000"
    },
    "done": true
  },
  "refurbished_furniture:recipes/misc/constructing/jungle_bath": {
    "criteria": {
      "has_copper_ingot": "2025-06-29 01:06:07 +0000"
    },
    "done": true
  },
  "mca:recipes/decorations/light_blue_spruce_crib": {
    "criteria": {
      "has_spruce_planks": "2025-06-29 00:51:07 +0000"
    },
    "done": true
  },
  "regions_unexplored:recipes/transportation/pine_boat": {
    "criteria": {
      "in_water": "2025-06-29 01:03:53 +0000"
    },
    "done": true
  },
  "mca:recipes/decorations/light_gray_oak_crib": {
    "criteria": {
      "has_oak_planks": "2025-06-29 00:47:58 +0000"
    },
    "done": true
  },
  "refurbished_furniture:recipes/misc/constructing/spruce_kitchen_cabinetry": {
    "criteria": {
      "has_spruce_planks": "2025-06-29 00:51:07 +0000"
    },
    "done": true
  },
  "minecraft:recipes/redstone/oak_trapdoor": {
    "criteria": {
      "has_planks": "2025-06-29 00:47:58 +0000"
    },
    "done": true
  },
  "refurbished_furniture:recipes/misc/constructing/black_cooler": {
    "criteria": {
      "has_planks": "2025-06-29 00:47:58 +0000"
    },
    "done": true
  },
  "mca:recipes/decorations/magenta_spruce_crib": {
    "criteria": {
      "has_spruce_planks": "2025-06-29 00:51:07 +0000"
    },
    "done": true
  },
  "regions_unexplored:recipes/transportation/eucalyptus_boat": {
    "criteria": {
      "in_water": "2025-06-29 01:03:53 +0000"
    },
    "done": true
  },
  "refurbished_furniture:recipes/misc/constructing/lime_lamp": {
    "criteria": {
      "has_planks": "2025-06-29 00:47:58 +0000"
    },
    "done": true
  },
  "minecraft:recipes/combat/stone_sword": {
    "criteria": {
      "has_cobblestone": "2025-06-29 00:57:17 +0000"
    },
    "done": true
  },
  "minecraft:recipes/decorations/cobblestone_wall": {
    "criteria": {
      "has_cobblestone": "2025-06-29 00:57:17 +0000"
    },
    "done": true
  },
  "refurbished_furniture:recipes/misc/television_remote": {
    "criteria": {
      "has_iron_nugget": "2025-06-29 01:04:27 +0000"
    },
    "done": true
  },
  "minecraft:recipes/tools/stone_axe": {
    "criteria": {
      "has_cobblestone": "2025-06-29 00:57:17 +0000"
    },
    "done": true
  },
  "refurbished_furniture:recipes/misc/constructing/dark_oak_basin": {
    "criteria": {
      "has_copper_ingot": "2025-06-29 01:06:07 +0000"
    },
    "done": true
  },
  "mca:recipes/decorations/blue_oak_crib": {
    "criteria": {
      "has_oak_planks": "2025-06-29 00:47:58 +0000"
    },
    "done": true
  },
  "refurbished_furniture:recipes/misc/constructing/cherry_basin": {
    "criteria": {
      "has_copper_ingot": "2025-06-29 01:06:07 +0000"
    },
    "done": true
  },
  "regions_unexplored:recipes/building_blocks/green_painted_planks": {
    "criteria": {
      "has_planks": "2025-06-29 00:47:58 +0000"
    },
    "done": true
  },
  "create:recipes/misc/crafting/materials/copper_nugget": {
    "criteria": {
      "has_item": "2025-06-29 01:06:07 +0000"
    },
    "done": true
  },
  "refurbished_furniture:recipes/misc/constructing/computer": {
    "criteria": {
      "has_copper_ingot": "2025-06-29 01:06:07 +0000"
    },
    "done": true
  },
  "minecraft:recipes/decorations/spruce_sign": {
    "criteria": {
      "has_planks": "2025-06-29 00:51:07 +0000"
    },
    "done": true
  },
  "refurbished_furniture:recipes/misc/constructing/magenta_cooler": {
    "criteria": {
      "has_planks": "2025-06-29 00:47:58 +0000"
    },
    "done": true
  },
  "securitycraft:recipes/redstone/laser_block": {
    "criteria": {
      "has_stone": "2025-06-29 00:57:17 +0000"
    },
    "done": true
  },
  "refurbished_furniture:recipes/misc/constructing/spruce_lattice_fence": {
    "criteria": {
      "has_spruce_planks": "2025-06-29 00:51:07 +0000"
    },
    "done": true
  },
  "refurbished_furniture:recipes/misc/constructing/light_blue_cooler": {
    "criteria": {
      "has_planks": "2025-06-29 00:47:58 +0000"
    },
    "done": true
  },
  "minecraft:recipes/combat/arrow": {
    "criteria": {
      "has_flint": "2025-06-29 01:04:12 +0000"
    },
    "done": true
  },
  "refurbished_furniture:recipes/misc/constructing/oak_mail_box": {
    "criteria": {
      "has_oak_planks": "2025-06-29 00:47:58 +0000"
    },
    "done": true
  },
  "refurbished_furniture:recipes/misc/constructing/pink_sofa": {
    "criteria": {
      "has_planks": "2025-06-29 00:47:58 +0000"
    },
    "done": true
  },
  "regions_unexplored:recipes/building_blocks/white_painted_planks": {
    "criteria": {
      "has_planks": "2025-06-29 00:47:58 +0000"
    },
    "done": true
  },
  "refurbished_furniture:recipes/misc/constructing/oak_bath": {
    "criteria": {
      "has_oak_planks": "2025-06-29 00:47:58 +0000"
    },
    "done": true
  },
  "refurbished_furniture:recipes/misc/constructing/brown_lamp": {
    "criteria": {
      "has_planks": "2025-06-29 00:47:58 +0000"
    },
    "done": true
  },
  "refurbished_furniture:recipes/misc/constructing/crimson_lattice_fence_gate": {
    "criteria": {
      "has_stick": "2025-06-29 00:51:19 +0000"
    },
    "done": true
  },
  "minecraft:recipes/decorations/smoker": {
    "criteria": {
      "has_furnace": "2025-06-29 00:57:43 +0000"
    },
    "done": true
  },
  "mca:recipes/decorations/purple_oak_crib": {
    "criteria": {
      "has_oak_planks": "2025-06-29 00:47:58 +0000"
    },
    "done": true
  },
  "mca:recipes/decorations/red_oak_crib": {
    "criteria": {
      "has_oak_planks": "2025-06-29 00:47:58 +0000"
    },
    "done": true
  },
  "refurbished_furniture:recipes/misc/constructing/lime_sofa": {
    "criteria": {
      "has_planks": "2025-06-29 00:47:58 +0000"
    },
    "done": true
  },
  "regions_unexplored:recipes/transportation/palm_boat": {
    "criteria": {
      "in_water": "2025-06-29 01:03:53 +0000"
    },
    "done": true
  },
  "regions_unexplored:recipes/building_blocks/light_gray_painted_planks": {
    "criteria": {
      "has_planks": "2025-06-29 00:47:58 +0000"
    },
    "done": true
  },
  "superbwarfare:main/epic_blueprint": {
    "criteria": {
      "0": "2025-06-29 01:04:24 +0000"
    },
    "done": true
  },
  "securitycraft:recipes/misc/reinforced_jungle_fence": {
    "criteria": {
      "has_stick": "2025-06-29 00:51:19 +0000"
    },
    "done": true
  },
  "minecraft:recipes/building_blocks/oak_stairs": {
    "criteria": {
      "has_planks": "2025-06-29 00:47:58 +0000"
    },
    "done": true
  },
  "create:recipes/building_blocks/copper_shingles_from_ingots_copper_stonecutting": {
    "criteria": {
      "has_ingots_copper": "2025-06-29 01:06:07 +0000"
    },
    "done": true
  },
  "create:recipes/misc/crafting/kinetics/fluid_pipe": {
    "criteria": {
      "has_item": "2025-06-29 01:06:07 +0000"
    },
    "done": true
  },
  "refurbished_furniture:recipes/misc/constructing/mangrove_basin": {
    "criteria": {
      "has_copper_ingot": "2025-06-29 01:06:07 +0000"
    },
    "done": true
  },
  "refurbished_furniture:recipes/misc/constructing/red_cooler": {
    "criteria": {
      "has_planks": "2025-06-29 00:47:58 +0000"
    },
    "done": true
  },
  "minecraft:recipes/decorations/chain": {
    "criteria": {
      "has_iron_nugget": "2025-06-29 01:04:27 +0000"
    },
    "done": true
  },
  "minecraft:recipes/decorations/oak_fence": {
    "criteria": {
      "has_planks": "2025-06-29 00:47:58 +0000"
    },
    "done": true
  },
  "regions_unexplored:recipes/transportation/socotra_boat": {
    "criteria": {
      "in_water": "2025-06-29 01:03:53 +0000"
    },
    "done": true
  },
  "securitycraft:recipes/misc/reinforced_warped_fence": {
    "criteria": {
      "has_stick": "2025-06-29 00:51:19 +0000"
    },
    "done": true
  },
  "refurbished_furniture:recipes/misc/constructing/oak_basin": {
    "criteria": {
      "has_oak_planks": "2025-06-29 00:47:58 +0000"
    },
    "done": true
  },
  "mca:recipes/decorations/purple_spruce_crib": {
    "criteria": {
      "has_spruce_planks": "2025-06-29 00:51:07 +0000"
    },
    "done": true
  },
  "regions_unexplored:recipes/building_blocks/light_blue_painted_planks": {
    "criteria": {
      "has_planks": "2025-06-29 00:47:58 +0000"
    },
    "done": true
  },
  "minecraft:recipes/building_blocks/spruce_wood": {
    "criteria": {
      "has_log": "2025-06-29 00:50:59 +0000"
    },
    "done": true
  },
  "refurbished_furniture:recipes/misc/constructing/dark_oak_bath": {
    "criteria": {
      "has_copper_ingot": "2025-06-29 01:06:07 +0000"
    },
    "done": true
  },
  "mca:recipes/decorations/magenta_oak_crib": {
    "criteria": {
      "has_oak_planks": "2025-06-29 00:47:58 +0000"
    },
    "done": true
  },
  "refurbished_furniture:recipes/misc/constructing/crimson_bath": {
    "criteria": {
      "has_copper_ingot": "2025-06-29 01:06:07 +0000"
    },
    "done": true
  },
  "regions_unexplored:recipes/building_blocks/yellow_painted_planks": {
    "criteria": {
      "has_planks": "2025-06-29 00:47:58 +0000"
    },
    "done": true
  },
  "minecraft:recipes/transportation/spruce_boat": {
    "criteria": {
      "in_water": "2025-06-29 01:03:53 +0000"
    },
    "done": true
  },
  "regions_unexplored:recipes/building_blocks/purple_painted_planks": {
    "criteria": {
      "has_planks": "2025-06-29 00:47:58 +0000"
    },
    "done": true
  },
  "refurbished_furniture:recipes/misc/constructing/mangrove_kitchen_sink": {
    "criteria": {
      "has_copper_ingot": "2025-06-29 01:06:07 +0000"
    },
    "done": true
  },
  "regions_unexplored:recipes/transportation/oak_boat": {
    "criteria": {
      "in_water": "2025-06-29 01:03:53 +0000"
    },
    "done": true
  },
  "securitycraft:recipes/redstone/reinforced_cherry_fence_gate": {
    "criteria": {
      "has_stick": "2025-06-29 00:51:19 +0000"
    },
    "done": true
  },
  "refurbished_furniture:recipes/misc/constructing/green_cooler": {
    "criteria": {
      "has_planks": "2025-06-29 00:47:58 +0000"
    },
    "done": true
  },
  "refurbished_furniture:recipes/misc/knife": {
    "criteria": {
      "has_leather": "2025-06-29 00:58:58 +0000"
    },
    "done": true
  },
  "refurbished_furniture:recipes/misc/workbench": {
    "criteria": {
      "has_planks": "2025-06-29 00:47:58 +0000"
    },
    "done": true
  },
  "refurbished_furniture:recipes/misc/constructing/brown_sofa": {
    "criteria": {
      "has_planks": "2025-06-29 00:47:58 +0000"
    },
    "done": true
  },
  "minecraft:husbandry/root": {
    "criteria": {
      "consumed_item": "2025-06-29 00:58:01 +0000"
    },
    "done": true
  },
  "minecraft:recipes/transportation/birch_boat": {
    "criteria": {
      "in_water": "2025-06-29 01:03:53 +0000"
    },
    "done": true
  },
  "refurbished_furniture:recipes/misc/constructing/light_blue_lamp": {
    "criteria": {
      "has_planks": "2025-06-29 00:47:58 +0000"
    },
    "done": true
  },
  "regions_unexplored:recipes/transportation/dead_boat": {
    "criteria": {
      "in_water": "2025-06-29 01:03:53 +0000"
    },
    "done": true
  },
  "refurbished_furniture:recipes/misc/constructing/blue_sofa": {
    "criteria": {
      "has_planks": "2025-06-29 00:47:58 +0000"
    },
    "done": true
  },
  "refurbished_furniture:recipes/misc/constructing/warped_basin": {
    "criteria": {
      "has_copper_ingot": "2025-06-29 01:06:07 +0000"
    },
    "done": true
  },
  "minecraft:recipes/transportation/oak_boat": {
    "criteria": {
      "in_water": "2025-06-29 01:03:53 +0000"
    },
    "done": true
  },
  "mca:recipes/decorations/cyan_spruce_crib": {
    "criteria": {
      "has_spruce_planks": "2025-06-29 00:51:07 +0000"
    },
    "done": true
  },
  "refurbished_furniture:recipes/misc/constructing/light_blue_stool": {
    "criteria": {
      "has_planks": "2025-06-29 00:47:58 +0000"
    },
    "done": true
  },
  "refurbished_furniture:recipes/misc/constructing/cherry_lattice_fence": {
    "criteria": {
      "has_stick": "2025-06-29 00:51:19 +0000"
    },
    "done": true
  },
  "minecraft:recipes/building_blocks/spruce_slab": {
    "criteria": {
      "has_planks": "2025-06-29 00:51:07 +0000"
    },
    "done": true
  },
  "mca:recipes/decorations/green_spruce_crib": {
    "criteria": {
      "has_spruce_planks": "2025-06-29 00:51:07 +0000"
    },
    "done": true
  },
  "securitycraft:recipes/redstone/reinforced_acacia_fence_gate": {
    "criteria": {
      "has_stick": "2025-06-29 00:51:19 +0000"
    },
    "done": true
  },
  "refurbished_furniture:recipes/misc/constructing/oak_chair": {
    "criteria": {
      "has_oak_planks": "2025-06-29 00:47:58 +0000"
    },
    "done": true
  },
  "minecraft:recipes/redstone/oak_button": {
    "criteria": {
      "has_planks": "2025-06-29 00:47:58 +0000"
    },
    "done": true
  },
  "refurbished_furniture:recipes/misc/constructing/white_cooler": {
    "criteria": {
      "has_planks": "2025-06-29 00:47:58 +0000"
    },
    "done": true
  },
  "refurbished_furniture:recipes/misc/constructing/spruce_cutting_board": {
    "criteria": {
      "has_spruce_planks": "2025-06-29 00:51:07 +0000"
    },
    "done": true
  },
  "create:recipes/misc/crafting/materials/transmitter": {
    "criteria": {
      "has_item": "2025-06-29 01:06:07 +0000"
    },
    "done": true
  },
  "create:recipes/misc/crafting/kinetics/fluid_valve": {
    "criteria": {
      "has_item": "2025-06-29 01:06:07 +0000"
    },
    "done": true
  },
  "refurbished_furniture:recipes/misc/constructing/blue_lamp": {
    "criteria": {
      "has_planks": "2025-06-29 00:47:58 +0000"
    },
    "done": true
  },
  "refurbished_furniture:recipes/misc/constructing/spruce_toilet": {
    "criteria": {
      "has_spruce_planks": "2025-06-29 00:51:07 +0000"
    },
    "done": true
  },
  "refurbished_furniture:recipes/misc/constructing/red_stool": {
    "criteria": {
      "has_planks": "2025-06-29 00:47:58 +0000"
    },
    "done": true
  },
  "minecraft:recipes/transportation/mangrove_boat": {
    "criteria": {
      "in_water": "2025-06-29 01:03:53 +0000"
    },
    "done": true
  },
  "refurbished_furniture:recipes/misc/constructing/crimson_kitchen_sink": {
    "criteria": {
      "has_copper_ingot": "2025-06-29 01:06:07 +0000"
    },
    "done": true
  },
  "refurbished_furniture:recipes/misc/wrench": {
    "criteria": {
      "has_leather": "2025-06-29 00:58:58 +0000"
    },
    "done": true
  },
  "create:recipes/decorations/copper_ladder_from_ingots_copper_stonecutting": {
    "criteria": {
      "has_ingots_copper": "2025-06-29 01:06:07 +0000"
    },
    "done": true
  },
  "securitycraft:recipes/misc/reinforced_cherry_fence": {
    "criteria": {
      "has_stick": "2025-06-29 00:51:19 +0000"
    },
    "done": true
  },
  "regions_unexplored:recipes/building_blocks/pink_painted_planks": {
    "criteria": {
      "has_planks": "2025-06-29 00:47:58 +0000"
    },
    "done": true
  },
  "minecraft:recipes/building_blocks/spruce_planks": {
    "criteria": {
      "has_logs": "2025-06-29 00:50:59 +0000"
    },
    "done": true
  },
  "mca:recipes/decorations/brown_spruce_crib": {
    "criteria": {
      "has_spruce_planks": "2025-06-29 00:51:07 +0000"
    },
    "done": true
  },
  "refurbished_furniture:recipes/misc/constructing/television": {
    "criteria": {
      "has_copper_ingot": "2025-06-29 01:06:07 +0000"
    },
    "done": true
  },
  "refurbished_furniture:recipes/misc/constructing/gray_lamp": {
    "criteria": {
      "has_planks": "2025-06-29 00:47:58 +0000"
    },
    "done": true
  },
  "refurbished_furniture:recipes/misc/constructing/warped_lattice_fence_gate": {
    "criteria": {
      "has_stick": "2025-06-29 00:51:19 +0000"
    },
    "done": true
  },
  "securitycraft:recipes/redstone/reinforced_warped_fence_gate": {
    "criteria": {
      "has_stick": "2025-06-29 00:51:19 +0000"
    },
    "done": true
  },
  "refurbished_furniture:recipes/misc/constructing/spruce_basin": {
    "criteria": {
      "has_spruce_planks": "2025-06-29 00:51:07 +0000"
    },
    "done": true
  },
  "refurbished_furniture:recipes/misc/constructing/jungle_basin": {
    "criteria": {
      "has_copper_ingot": "2025-06-29 01:06:07 +0000"
    },
    "done": true
  },
  "regions_unexplored:recipes/transportation/mauve_boat": {
    "criteria": {
      "in_water": "2025-06-29 01:03:53 +0000"
    },
    "done": true
  },
  "refurbished_furniture:recipes/misc/constructing/light_blue_sofa": {
    "criteria": {
      "has_planks": "2025-06-29 00:47:58 +0000"
    },
    "done": true
  },
  "refurbished_furniture:recipes/misc/constructing/black_sofa": {
    "criteria": {
      "has_planks": "2025-06-29 00:47:58 +0000"
    },
    "done": true
  },
  "regions_unexplored:recipes/transportation/redwood_boat": {
    "criteria": {
      "in_water": "2025-06-29 01:03:53 +0000"
    },
    "done": true
  },
  "refurbished_furniture:recipes/misc/constructing/purple_sofa": {
    "criteria": {
      "has_planks": "2025-06-29 00:47:58 +0000"
    },
    "done": true
  },
  "create:recipes/decorations/copper_scaffolding_from_ingots_copper_stonecutting": {
    "criteria": {
      "has_ingots_copper": "2025-06-29 01:06:07 +0000"
    },
    "done": true
  },
  "minecraft:recipes/tools/flint_and_steel": {
    "criteria": {
      "has_flint": "2025-06-29 01:04:12 +0000"
    },
    "done": true
  },
  "mca:recipes/decorations/lime_oak_crib": {
    "criteria": {
      "has_oak_planks": "2025-06-29 00:47:58 +0000"
    },
    "done": true
  },
  "regions_unexplored:regions_explored": {
    "criteria": {
      "maple_forest": "2025-06-29 00:50:49 +0000"
    },
    "done": false
  },
  "refurbished_furniture:recipes/misc/constructing/oak_lattice_fence": {
    "criteria": {
      "has_oak_planks": "2025-06-29 00:47:58 +0000"
    },
    "done": true
  },
  "refurbished_furniture:recipes/misc/constructing/gray_cooler": {
    "criteria": {
      "has_planks": "2025-06-29 00:47:58 +0000"
    },
    "done": true
  },
  "minecraft:recipes/tools/wooden_pickaxe": {
    "criteria": {
      "has_stick": "2025-06-29 00:51:19 +0000"
    },
    "done": true
  },
  "regions_unexplored:recipes/building_blocks/magenta_painted_planks": {
    "criteria": {
      "has_planks": "2025-06-29 00:47:58 +0000"
    },
    "done": true
  },
  "refurbished_furniture:recipes/misc/constructing/light_gray_stool": {
    "criteria": {
      "has_planks": "2025-06-29 00:47:58 +0000"
    },
    "done": true
  },
  "refurbished_furniture:recipes/misc/constructing/white_stool": {
    "criteria": {
      "has_planks": "2025-06-29 00:47:58 +0000"
    },
    "done": true
  },
  "sophisticatedbackpacks:recipes/misc/upgrade_base": {
    "criteria": {
      "has_leather": "2025-06-29 00:58:58 +0000"
    },
    "done": true
  },
  "minecraft:recipes/redstone/oak_pressure_plate": {
    "criteria": {
      "has_planks": "2025-06-29 00:47:58 +0000"
    },
    "done": true
  },
  "refurbished_furniture:recipes/misc/constructing/mangrove_lattice_fence": {
    "criteria": {
      "has_stick": "2025-06-29 00:51:19 +0000"
    },
    "done": true
  },
  "regions_unexplored:recipes/transportation/baobab_boat": {
    "criteria": {
      "in_water": "2025-06-29 01:03:53 +0000"
    },
    "done": true
  },
  "refurbished_furniture:recipes/misc/constructing/cherry_lattice_fence_gate": {
    "criteria": {
      "has_stick": "2025-06-29 00:51:19 +0000"
    },
    "done": true
  },
  "securitycraft:recipes/redstone/reinforced_mangrove_fence_gate": {
    "criteria": {
      "has_stick": "2025-06-29 00:51:19 +0000"
    },
    "done": true
  },
  "refurbished_furniture:recipes/misc/constructing/yellow_stool": {
    "criteria": {
      "has_planks": "2025-06-29 00:47:58 +0000"
    },
    "done": true
  },
  "mca:recipes/decorations/black_oak_crib": {
    "criteria": {
      "has_oak_planks": "2025-06-29 00:47:58 +0000"
    },
    "done": true
  },
  "refurbished_furniture:recipes/misc/constructing/black_lamp": {
    "criteria": {
      "has_planks": "2025-06-29 00:47:58 +0000"
    },
    "done": true
  },
  "minecraft:recipes/redstone/spruce_trapdoor": {
    "criteria": {
      "has_planks": "2025-06-29 00:51:07 +0000"
    },
    "done": true
  },
  "minecraft:recipes/redstone/spruce_door": {
    "criteria": {
      "has_planks": "2025-06-29 00:51:07 +0000"
    },
    "done": true
  },
  "minecraft:recipes/redstone/spruce_fence_gate": {
    "criteria": {
      "has_planks": "2025-06-29 00:51:07 +0000"
    },
    "done": true
  },
  "securitycraft:recipes/misc/reinforced_mangrove_fence": {
    "criteria": {
      "has_stick": "2025-06-29 00:51:19 +0000"
    },
    "done": true
  },
  "securitycraft:recipes/building_blocks/reinforced_andesite": {
    "criteria": {
      "has_cobblestone": "2025-06-29 00:57:17 +0000"
    },
    "done": true
  },
  "create:recipes/misc/crafting/kinetics/hose_pulley": {
    "criteria": {
      "has_item": "2025-06-29 01:06:07 +0000"
    },
    "done": true
  },
  "regions_unexplored:pioneer": {
    "criteria": {
      "maple_forest": "2025-06-29 00:50:49 +0000"
    },
    "done": false
  },
  "mca:recipes/decorations/gray_spruce_crib": {
    "criteria": {
      "has_spruce_planks": "2025-06-29 00:51:07 +0000"
    },
    "done": true
  },
  "refurbished_furniture:recipes/misc/constructing/pink_lamp": {
    "criteria": {
      "has_planks": "2025-06-29 00:47:58 +0000"
    },
    "done": true
  },
  "refurbished_furniture:recipes/misc/constructing/spruce_desk": {
    "criteria": {
      "has_spruce_planks": "2025-06-29 00:51:07 +0000"
    },
    "done": true
  },
  "refurbished_furniture:recipes/misc/constructing/lime_cooler": {
    "criteria": {
      "has_planks": "2025-06-29 00:47:58 +0000"
    },
    "done": true
  },
  "refurbished_furniture:recipes/misc/constructing/oak_storage_cabinet": {
    "criteria": {
      "has_oak_planks": "2025-06-29 00:47:58 +0000"
    },
    "done": true
  },
  "refurbished_furniture:recipes/misc/constructing/spruce_storage_cabinet": {
    "criteria": {
      "has_spruce_planks": "2025-06-29 00:51:07 +0000"
    },
    "done": true
  },
  "mca:recipes/decorations/pink_oak_crib": {
    "criteria": {
      "has_oak_planks": "2025-06-29 00:47:58 +0000"
    },
    "done": true
  },
  "refurbished_furniture:recipes/misc/constructing/cherry_toilet": {
    "criteria": {
      "has_copper_ingot": "2025-06-29 01:06:07 +0000"
    },
    "done": true
  },
  "mca:recipes/decorations/orange_oak_crib": {
    "criteria": {
      "has_oak_planks": "2025-06-29 00:47:58 +0000"
    },
    "done": true
  },
  "refurbished_furniture:recipes/misc/constructing/gray_stool": {
    "criteria": {
      "has_planks": "2025-06-29 00:47:58 +0000"
    },
    "done": true
  },
  "refurbished_furniture:recipes/misc/constructing/spruce_chair": {
    "criteria": {
      "has_spruce_planks": "2025-06-29 00:51:07 +0000"
    },
    "done": true
  },
  "securitycraft:recipes/building_blocks/reinforced_diorite": {
    "criteria": {
      "has_cobblestone": "2025-06-29 00:57:17 +0000"
    },
    "done": true
  },
  "mca:recipes/decorations/brown_oak_crib": {
    "criteria": {
      "has_oak_planks": "2025-06-29 00:47:58 +0000"
    },
    "done": true
  },
  "refurbished_furniture:recipes/misc/constructing/acacia_lattice_fence_gate": {
    "criteria": {
      "has_stick": "2025-06-29 00:51:19 +0000"
    },
    "done": true
  },
  "refurbished_furniture:recipes/misc/constructing/pink_cooler": {
    "criteria": {
      "has_planks": "2025-06-29 00:47:58 +0000"
    },
    "done": true
  },
  "create:recipes/building_blocks/oak_window": {
    "criteria": {
      "has_ingredient": "2025-06-29 00:47:58 +0000"
    },
    "done": true
  },
  "mca:recipes/decorations/yellow_oak_crib": {
    "criteria": {
      "has_oak_planks": "2025-06-29 00:47:58 +0000"
    },
    "done": true
  },
  "mca:recipes/decorations/lime_spruce_crib": {
    "criteria": {
      "has_spruce_planks": "2025-06-29 00:51:07 +0000"
    },
    "done": true
  },
  "refurbished_furniture:recipes/misc/constructing/white_sofa": {
    "criteria": {
      "has_planks": "2025-06-29 00:47:58 +0000"
    },
    "done": true
  },
  "minecraft:adventure/kill_a_mob": {
    "criteria": {
      "minecraft:zombie": "2025-06-29 00:56:32 +0000"
    },
    "done": true
  },
  "minecraft:adventure/adventuring_time": {
    "criteria": {
      "minecraft:river": "2025-06-29 01:03:55 +0000",
      "minecraft:grove": "2025-06-29 00:43:28 +0000",
      "minecraft:forest": "2025-06-29 00:46:09 +0000",
      "minecraft:plains": "2025-06-29 00:54:20 +0000"
    },
    "done": false
  },
  "refurbished_furniture:recipes/misc/constructing/oak_table": {
    "criteria": {
      "has_oak_planks": "2025-06-29 00:47:58 +0000"
    },
    "done": true
  },
  "superbwarfare:recipes/misc/hunting_rifle_blueprint": {
    "criteria": {
      "has_hunting_rifle_blueprint": "2025-06-29 01:04:24 +0000"
    },
    "done": true
  },
  "refurbished_furniture:recipes/misc/constructing/cyan_sofa": {
    "criteria": {
      "has_planks": "2025-06-29 00:47:58 +0000"
    },
    "done": true
  },
  "minecraft:recipes/building_blocks/cobblestone_stairs_from_cobblestone_stonecutting": {
    "criteria": {
      "has_cobblestone": "2025-06-29 00:57:17 +0000"
    },
    "done": true
  },
  "refurbished_furniture:recipes/misc/constructing/yellow_cooler": {
    "criteria": {
      "has_planks": "2025-06-29 00:47:58 +0000"
    },
    "done": true
  },
  "refurbished_furniture:recipes/misc/constructing/cherry_kitchen_sink": {
    "criteria": {
      "has_copper_ingot": "2025-06-29 01:06:07 +0000"
    },
    "done": true
  },
  "minecraft:husbandry/balanced_diet": {
    "criteria": {
      "cooked_beef": "2025-06-29 00:58:01 +0000"
    },
    "done": false
  },
  "refurbished_furniture:recipes/misc/constructing/black_stool": {
    "criteria": {
      "has_planks": "2025-06-29 00:47:58 +0000"
    },
    "done": true
  },
  "minecraft:recipes/redstone/tnt": {
    "criteria": {
      "has_gunpowder": "2025-06-29 01:00:29 +0000"
    },
    "done": true
  },
  "superbwarfare:main/root": {
    "criteria": {
      "0": "2025-06-29 00:43:28 +0000"
    },
    "done": true
  },
  "refurbished_furniture:recipes/misc/constructing/blue_cooler": {
    "criteria": {
      "has_planks": "2025-06-29 00:47:58 +0000"
    },
    "done": true
  },
  "refurbished_furniture:recipes/misc/constructing/warped_lattice_fence": {
    "criteria": {
      "has_stick": "2025-06-29 00:51:19 +0000"
    },
    "done": true
  },
  "minecraft:recipes/tools/stone_hoe": {
    "criteria": {
      "has_cobblestone": "2025-06-29 00:57:17 +0000"
    },
    "done": true
  },
  "regions_unexplored:recipes/transportation/willow_boat": {
    "criteria": {
      "in_water": "2025-06-29 01:03:53 +0000"
    },
    "done": true
  },
  "minecraft:recipes/building_blocks/spruce_stairs": {
    "criteria": {
      "has_planks": "2025-06-29 00:51:07 +0000"
    },
    "done": true
  },
  "refurbished_furniture:recipes/misc/constructing/orange_cooler": {
    "criteria": {
      "has_planks": "2025-06-29 00:47:58 +0000"
    },
    "done": true
  },
  "refurbished_furniture:recipes/misc/constructing/spruce_drawer": {
    "criteria": {
      "has_spruce_planks": "2025-06-29 00:51:07 +0000"
    },
    "done": true
  },
  "refurbished_furniture:recipes/misc/constructing/birch_lattice_fence_gate": {
    "criteria": {
      "has_stick": "2025-06-29 00:51:19 +0000"
    },
    "done": true
  },
  "refurbished_furniture:recipes/misc/constructing/cyan_lamp": {
    "criteria": {
      "has_planks": "2025-06-29 00:47:58 +0000"
    },
    "done": true
  },
  "mca:recipes/decorations/light_blue_oak_crib": {
    "criteria": {
      "has_oak_planks": "2025-06-29 00:47:58 +0000"
    },
    "done": true
  },
  "refurbished_furniture:recipes/misc/constructing/gray_sofa": {
    "criteria": {
      "has_planks": "2025-06-29 00:47:58 +0000"
    },
    "done": true
  },
  "minecraft:story/root": {
    "criteria": {
      "crafting_table": "2025-06-29 00:51:12 +0000"
    },
    "done": true
  },
  "mca:recipes/decorations/gray_oak_crib": {
    "criteria": {
      "has_oak_planks": "2025-06-29 00:47:58 +0000"
    },
    "done": true
  },
  "securitycraft:recipes/misc/reinforced_spruce_fence": {
    "criteria": {
      "has_stick": "2025-06-29 00:51:19 +0000"
    },
    "done": true
  },
  "refurbished_furniture:recipes/misc/constructing/purple_lamp": {
    "criteria": {
      "has_planks": "2025-06-29 00:47:58 +0000"
    },
    "done": true
  },
  "regions_unexplored:recipes/transportation/joshua_boat": {
    "criteria": {
      "in_water": "2025-06-29 01:03:53 +0000"
    },
    "done": true
  },
  "minecraft:recipes/transportation/dark_oak_boat": {
    "criteria": {
      "in_water": "2025-06-29 01:03:53 +0000"
    },
    "done": true
  },
  "minecraft:recipes/food/cooked_beef_from_campfire_cooking": {
    "criteria": {
      "has_beef": "2025-06-29 00:57:29 +0000"
    },
    "done": true
  },
  "refurbished_furniture:recipes/misc/constructing/warped_toilet": {
    "criteria": {
      "has_copper_ingot": "2025-06-29 01:06:07 +0000"
    },
    "done": true
  },
  "refurbished_furniture:recipes/misc/constructing/pink_stool": {
    "criteria": {
      "has_planks": "2025-06-29 00:47:58 +0000"
    },
    "done": true
  },
  "DataVersion": 3465
}